LICENSE
MANIFEST.in
README.rst
setup.py
tox.ini
moreutils/__init__.py
moreutils/config.py
moreutils/exceptions.py
moreutils/log.py
moreutils/retry.py
moreutils.egg-info/PKG-INFO
moreutils.egg-info/SOURCES.txt
moreutils.egg-info/dependency_links.txt
moreutils.egg-info/entry_points.txt
moreutils.egg-info/requires.txt
moreutils.egg-info/top_level.txt