Metadata-Version: 1.1
Name: moreutils
Version: 0.0.2
Summary: Standard library augmenting utilities and helpers.
Home-page: https://github.com/johannestaas/moreutils
Author: Johan Nestaas
Author-email: johannestaas@gmail.com
License: GPLv3
Keywords: stdlib utils
Platform: UNKNOWN
Classifier: Development Status :: 3 - Alpha
Classifier: Environment :: Console
Classifier: Environment :: X11 Applications :: Qt
Classifier: Environment :: MacOS X
Classifier: Environment :: Win32 (MS Windows)
Classifier: Operating System :: POSIX
Classifier: Operating System :: MacOS :: MacOS X
Classifier: Operating System :: Microsoft :: Windows
Classifier: Programming Language :: Python
